frasco_search.py
setup.py
frasco_search.egg-info/PKG-INFO
frasco_search.egg-info/SOURCES.txt
frasco_search.egg-info/dependency_links.txt
frasco_search.egg-info/not-zip-safe
frasco_search.egg-info/requires.txt
frasco_search.egg-info/top_level.txt