Metadata-Version: 1.0
Name: frasco-search
Version: 0.1.1
Summary: Elastisearch integration for Frasco
Home-page: http://github.com/frascoweb/frasco-search
Author: Maxime Bouroumeau-Fuseau
Author-email: maxime.bouroumeau@gmail.com
License: MIT
Platform: any
